ragmetrics/__init__.py
ragmetrics/api.py
ragmetrics/criteria.py
ragmetrics/dataset.py
ragmetrics/experiments.py
ragmetrics/reviews.py
ragmetrics/tasks.py
ragmetrics/trace.py
ragmetrics/utils.py
ragmetrics/integrations/__init__.py
ragmetrics/integrations/agents.py
ragmetrics_client-0.2.1.dist-info/licenses/LICENSE
ragmetrics_client-0.2.1.dist-info/METADATA
ragmetrics_client-0.2.1.dist-info/WHEEL
ragmetrics_client-0.2.1.dist-info/top_level.txt
ragmetrics_client-0.2.1.dist-info/RECORD
