Metadata-Version: 2.4
Name: ragmetrics-client
Version: 0.2.1
Summary: Monitor your LLM calls. Test your LLM app.
Author: ragmetrics
License-Expression: MIT
Project-URL: Homepage, https://ragmetrics.ai
Project-URL: Repository, https://github.com/RagMetrics/ragmetrics-package
Keywords: llm,evaluation,monitoring,rag
Classifier: Programming Language :: Python :: 3
Classifier: Programming Language :: Python :: 3.6
Classifier: Programming Language :: Python :: 3.7
Classifier: Programming Language :: Python :: 3.8
Classifier: Programming Language :: Python :: 3.9
Classifier: Programming Language :: Python :: 3.10
Classifier: Programming Language :: Python :: 3.11
Classifier: Operating System :: OS Independent
Requires-Python: >=3.6
License-File: LICENSE
Requires-Dist: requests>=2.20.0
Requires-Dist: iso8601
Requires-Dist: tqdm
Dynamic: license-file
